pogucam/__init__.py
pogucam/buffers.py
pogucam/explore_u24_uni.py
pogucam/installation.md
pogucam/mqimr.py
pogucam/mqims.py
pogucam/text_write.py
pogucam-0.1.27.dist-info/METADATA
pogucam-0.1.27.dist-info/WHEEL
pogucam-0.1.27.dist-info/entry_points.txt
pogucam-0.1.27.dist-info/RECORD
