Metadata-Version: 2.4
Name: pogucam
Version: 0.1.27
Summary: Add your description here
Author-email: jaromrax <jaromrax@gmail.com>
Requires-Python: >=3.12
Requires-Dist: astropy>=7.1.0
Requires-Dist: click>=8.2.1
Requires-Dist: console>=0.9911
Requires-Dist: numpy>=2.3.0
Requires-Dist: opencv-python>=4.11.0.86
Requires-Dist: paho-mqtt>=2.0.0
Requires-Dist: pillow>=11.2.1
Requires-Dist: pyqt6>=6.9.1
Requires-Dist: requests>=2.32.4
